dsm.py
dsm/__init__.py
dsm/fields.py
dsm-0.5.3.dist-info/LICENSE
dsm-0.5.3.dist-info/METADATA
dsm-0.5.3.dist-info/WHEEL
dsm-0.5.3.dist-info/top_level.txt
dsm-0.5.3.dist-info/zip-safe
dsm-0.5.3.dist-info/RECORD
