Metadata-Version: 2.1
Name: dsm
Version: 0.5.3
Summary: Damn simple finite state machine 
Home-page: https://github.com/marcinn/dsm
Author: Marcin Nowak
Author-email: marcin.j.nowak@gmail.com
License: UNKNOWN
Keywords: fsm state machine
Platform: UNKNOWN
Classifier: Development Status :: 4 - Beta
Classifier: License :: OSI Approved :: BSD License
Classifier: Operating System :: OS Independent
Classifier: Framework :: Django
Classifier: Framework :: Django :: 3.0
Classifier: Framework :: Django :: 2.2
Classifier: Framework :: Django :: 2.1
Classifier: Framework :: Django :: 2.0
Classifier: Programming Language :: Python
Classifier: Programming Language :: Python :: 3.5
Classifier: Programming Language :: Python :: 3.6
Classifier: Programming Language :: Python :: 3.7
Classifier: Programming Language :: Python :: 3.8
Classifier: Topic :: Software Development :: Libraries :: Python Modules
Classifier: Intended Audience :: Developers
Requires-Dist: observable
Requires-Dist: six
